setup.py
nomun_khet_rpigui/__init__.py
nomun_khet_rpigui.egg-info/PKG-INFO
nomun_khet_rpigui.egg-info/SOURCES.txt
nomun_khet_rpigui.egg-info/dependency_links.txt
nomun_khet_rpigui.egg-info/not-zip-safe
nomun_khet_rpigui.egg-info/top_level.txt