Metadata-Version: 1.0
Name: nomun-khet-rpigui
Version: 0.2.0.0
Summary: ene san Nomun Khet LLC-n raspberru pi-n surgaltad zoriulagdsan bolno
Home-page: http://elecbook.net
Author: Garid Zorigoo
Author-email: garidzorgioo@gmail.com
License: NK llc
Platform: UNKNOWN
